dddttt.py
setup.py
ddd_ttt.egg-info/PKG-INFO
ddd_ttt.egg-info/SOURCES.txt
ddd_ttt.egg-info/dependency_links.txt
ddd_ttt.egg-info/not-zip-safe
ddd_ttt.egg-info/top_level.txt