Metadata-Version: 1.0
Name: ddd-ttt
Version: 0.1.dev49
Summary: test project (please ignore)
Home-page: UNKNOWN
Author: Holger Krekel
Author-email: holger at merlinux.eu
License: UNKNOWN
Platform: UNKNOWN
